booster/__init__.py
booster/py.typed
booster/adapters/__init__.py
booster/adapters/manager/__init__.py
booster/adapters/manager/base.py
booster/adapters/manager/npm.py
booster/adapters/manager/utils.py
booster/cli/__init__.py
booster/cli/main.py
apg_booster-0.1.2.dist-info/METADATA
apg_booster-0.1.2.dist-info/WHEEL
apg_booster-0.1.2.dist-info/entry_points.txt
apg_booster-0.1.2.dist-info/RECORD
