Metadata-Version: 2.4
Name: apg-booster
Version: 0.1.2
Summary: A CLI tool to create and manage projects with a template
Project-URL: Documentation, https://github.com/ahnopologetic/booster
Project-URL: Source, https://github.com/ahnopologetic/booster
Project-URL: Tracker, https://github.com/ahnopologetic/booster/issues
Author-email: ahnopologetic <stahn1995@gmail.com>
License: MIT
Classifier: License :: OSI Approved :: MIT License
Classifier: Operating System :: OS Independent
Classifier: Programming Language :: Python :: 3
Classifier: Programming Language :: Python :: 3.9
Classifier: Programming Language :: Python :: 3.10
Classifier: Programming Language :: Python :: 3.11
Classifier: Programming Language :: Python :: 3.12
Classifier: Programming Language :: Python :: 3.13
Classifier: Topic :: Internet :: WWW/HTTP :: HTTP Servers
Requires-Python: >=3.9
Requires-Dist: click>=8.1.8
